spoonbill/__init__.py
spoonbill/datastores/__init__.py
spoonbill/datastores/base.py
spoonbill/datastores/buckets.py
spoonbill/datastores/cosmos.py
spoonbill/datastores/dynamodb.py
spoonbill/datastores/filesystem.py
spoonbill/datastores/firestore.py
spoonbill/datastores/inmemory.py
spoonbill/datastores/jsonstore.py
spoonbill/datastores/leveldb.py
spoonbill/datastores/lmdb.py
spoonbill/datastores/modal.py
spoonbill/datastores/mongodb.py
spoonbill/datastores/pysos.py
spoonbill/datastores/rdict.py
spoonbill/datastores/redis.py
spoonbill/datastores/rocksdb.py
spoonbill/datastores/safetensors.py
spoonbill/datastores/shelve.py
spoonbill/datastores/speedb.py
spoonbill/datastores/unqlite.py
spoonbill/datastores/utils.py
spoonbill/filesystem.py
spoonbill_framework-0.1.1.dist-info/LICENSE
spoonbill_framework-0.1.1.dist-info/METADATA
spoonbill_framework-0.1.1.dist-info/WHEEL
spoonbill_framework-0.1.1.dist-info/RECORD
