Metadata-Version: 2.1
Name: spoonbill-framework
Version: 0.1.1
Summary: A lightweight, universal interface for Key-Values data stores
License: LICENSE
Keywords: dict,key-value,gcp,azure,aws,s3,lmdb,pysos,redis,dynamodb,mongodb,cosmosdb,safetensors,unqlite
Author: xdssio
Author-email: jonathan@xdss.io
Requires-Python: >=3.7,<4.0
Classifier: License :: OSI Approved :: MIT License
Classifier: License :: Other/Proprietary License
Classifier: Programming Language :: Python
Classifier: Programming Language :: Python :: 3
Classifier: Programming Language :: Python :: 3.7
Classifier: Programming Language :: Python :: 3.8
Classifier: Programming Language :: Python :: 3.9
Classifier: Programming Language :: Python :: 3.10
Classifier: Programming Language :: Python :: 3.11
Provides-Extra: aws
Provides-Extra: azure
Provides-Extra: dev
Provides-Extra: gcp
Provides-Extra: json
Provides-Extra: lmdbm
Provides-Extra: modal
Provides-Extra: mongodb
Provides-Extra: pysos
Provides-Extra: redis
Provides-Extra: rocksdb
Provides-Extra: safetensors
Provides-Extra: speedb
Provides-Extra: unqlite
Requires-Dist: cloudpickle
Requires-Dist: fsspec
